random_caps/__init__.py
random_caps/random_cap.py
random_caps-0.0.6.dist-info/METADATA
random_caps-0.0.6.dist-info/WHEEL
random_caps-0.0.6.dist-info/licenses/LICENSE
random_caps-0.0.6.dist-info/RECORD
